atomdb/__init__.py
atomdb/__main__.py
atomdb/periodic.py
atomdb/promolecule.py
atomdb/species.py
atomdb/utils.py
atomdb/data/atoms_uhf_def2svpd.tar.gz
atomdb/data/c6cp04533b1.csv
atomdb/data/data_info.csv
atomdb/data/database_beta_1.3.0.h5
atomdb/data/density.out.tar.gz
atomdb/data/elements_data.csv
atomdb/data/multiplicities_table.csv
atomdb/data/slater_atom.tar.xz
atomdb/datasets/__init__.py
atomdb/datasets/tools.py
atomdb/datasets/gaussian/__init__.py
atomdb/datasets/gaussian/run.py
atomdb/datasets/hci/__init__.py
atomdb/datasets/hci/run.py
atomdb/datasets/nist/__init__.py
atomdb/datasets/nist/run.py
atomdb/datasets/numeric/__init__.py
atomdb/datasets/numeric/run.py
atomdb/datasets/slater/__init__.py
atomdb/datasets/slater/run.py
atomdb/datasets/uhf_augccpvdz/__init__.py
atomdb/datasets/uhf_augccpvdz/run.py
atomdb/test/test_api.py
atomdb/test/test_gaussian.py
atomdb/test/test_gaussian_dev.py
atomdb/test/test_hci.py
atomdb/test/test_nist.py
atomdb/test/test_numeric.py
atomdb/test/test_periodic.py
atomdb/test/test_promolecule.py
atomdb/test/test_utils.py
atomdb/test/test_wfn_slater.py
atomdb/test/test_wfn_slater_dev.py
atomdb/test/data/gaussian/atom_001_H_N02_M1_uhf_def2svpd_g09.fchk
atomdb/test/data/gaussian/atom_018_Ar_N18_M1_uhf_def2svpd_g09.fchk
atomdb/test/data/gaussian/db/B_000_002_000.msg
atomdb/test/data/gaussian/db/Be_000_001_000.msg
atomdb/test/data/hci/db/H_000_002_000.msg
atomdb/test/data/nist/db/C_-01_004_000.msg
atomdb/test/data/nist/db/C_000_003_000.msg
atomdb/test/data/nist/db/C_001_002_000.msg
atomdb/test/data/nist/db/H_000_002_000.msg
atomdb/test/data/numeric/db/001_q-01_m01_numeric_gradient.npy
atomdb/test/data/numeric/db/001_q-01_m01_numeric_laplacian.npy
atomdb/test/data/numeric/db/001_q000_m02_numeric_gradient.npy
atomdb/test/data/numeric/db/001_q000_m02_numeric_laplacian.npy
atomdb/test/data/numeric/db/004_q000_m01_numeric_gradient.npy
atomdb/test/data/numeric/db/004_q000_m01_numeric_laplacian.npy
qc_AtomDB-0.0.2.post5.dist-info/LICENSE
qc_AtomDB-0.0.2.post5.dist-info/METADATA
qc_AtomDB-0.0.2.post5.dist-info/WHEEL
qc_AtomDB-0.0.2.post5.dist-info/top_level.txt
qc_AtomDB-0.0.2.post5.dist-info/RECORD
