Metadata-Version: 2.1
Name: qc-AtomDB
Version: 0.0.2.post5
Summary: AtomDB is a database of atomic and ionic properties.
Author-email: QC-Devs Community <qcdevs@gmail.com>
License: GPL-3.0-or-later
Project-URL: Documentation, https://atomdb.qcdevs.org
Project-URL: Issues, https://github.com/theochem/atomdb/issues
Project-URL: Source, https://github.com/theochem/atomdb/
Project-URL: Changelog, https://github.com/theochem/atomdb/blob/main/CHANGELOG.md
Classifier: Development Status :: 5 - Production/Stable
Classifier: Environment :: Console
Classifier: License :: OSI Approved :: GNU General Public License v3 or later (GPLv3+)
Classifier: Operating System :: POSIX :: Linux
Classifier: Topic :: Scientific/Engineering :: Physics
Classifier: Topic :: Scientific/Engineering :: Chemistry
Classifier: Intended Audience :: Science/Research
Classifier: Intended Audience :: Education
Classifier: Natural Language :: English
Classifier: Programming Language :: Python :: 3.9
Classifier: Programming Language :: Python :: 3.10
Classifier: Programming Language :: Python :: 3.11
Classifier: Programming Language :: Python :: 3.12
Requires-Python: >=3.9
License-File: LICENSE
Requires-Dist: numpy >=1.16
Requires-Dist: scipy >=1.4
Requires-Dist: msgpack >=1.0.0
Requires-Dist: msgpack-numpy >=0.4.8
Requires-Dist: h5py >=3.6.0
Requires-Dist: importlib-resources >=3.0.0
Requires-Dist: pooch >=1.8.1
Provides-Extra: dev
Requires-Dist: pytest >=8.3.3 ; extra == 'dev'
Requires-Dist: pyscf ; extra == 'dev'
Requires-Dist: qc-gbasis ; extra == 'dev'
Requires-Dist: qc-iodata ; extra == 'dev'
Provides-Extra: doc
Requires-Dist: ipython ; extra == 'doc'
Requires-Dist: numpydoc ; extra == 'doc'
Requires-Dist: sphinx-copybutton ; extra == 'doc'
Requires-Dist: sphinx-autoapi ; extra == 'doc'
Requires-Dist: nbsphinx ; extra == 'doc'
Requires-Dist: nbconvert ; extra == 'doc'
Requires-Dist: sphinx-rtd-theme ; extra == 'doc'
Requires-Dist: sphinxcontrib-bibtex ; extra == 'doc'
Requires-Dist: sphinx-autodoc-typehints ; extra == 'doc'
Requires-Dist: docutils ==0.16 ; extra == 'doc'
Requires-Dist: nbsphinx-link ; extra == 'doc'
Provides-Extra: test_extra
Requires-Dist: pytest-md ; extra == 'test_extra'
Requires-Dist: pytest-emoji ; extra == 'test_extra'
Requires-Dist: pytest-cov ; extra == 'test_extra'
